drobo/__init__.py
drobo/cli.py
drobo/commands.py
drobo/config.py
drobo/dropbox_client.py
drobo-1.0.0.dist-info/licenses/LICENSE
drobo-1.0.0.dist-info/METADATA
drobo-1.0.0.dist-info/WHEEL
drobo-1.0.0.dist-info/entry_points.txt
drobo-1.0.0.dist-info/top_level.txt
drobo-1.0.0.dist-info/RECORD
