Metadata-Version: 2.4
Name: drobo
Version: 1.0.0
Summary: A Dropbox CLI
Author: rtrimble13
License: MIT
Project-URL: Homepage, https://github.com/rtrimble13/drobo
Project-URL: Repository, https://github.com/rtrimble13/drobo
Project-URL: Issues, https://github.com/rtrimble13/drobo/issues
Project-URL: Changelog, https://github.com/rtrimble13/drobo/releases
Classifier: Development Status :: 3 - Alpha
Classifier: Intended Audience :: Developers
Classifier: License :: OSI Approved :: MIT License
Classifier: Programming Language :: Python :: 3
Classifier: Programming Language :: Python :: 3.10
Classifier: Programming Language :: Python :: 3.11
Classifier: Programming Language :: Python :: 3.12
Classifier: Programming Language :: Python :: 3.13
Classifier: Topic :: Utilities
Requires-Python: >=3.10
License-File: LICENSE
Requires-Dist: click>=8.0.0
Requires-Dist: dropbox>=11.0.0
Requires-Dist: configistate>=1.0.0
Provides-Extra: dev
Requires-Dist: pytest>=7.0.0; extra == "dev"
Requires-Dist: pytest-cov>=4.0.0; extra == "dev"
Requires-Dist: pytest-mock>=3.10.0; extra == "dev"
Requires-Dist: black>=22.0.0; extra == "dev"
Requires-Dist: flake8>=5.0.0; extra == "dev"
Requires-Dist: isort>=5.0.0; extra == "dev"
Dynamic: license-file
